AUTHORS.rst
CONTRIBUTING.rst
HISTORY.rst
LICENSE
MANIFEST.in
README.rst
setup.cfg
setup.py
docs/Makefile
docs/authors.rst
docs/conf.py
docs/configuration.rst
docs/contributing.rst
docs/history.rst
docs/index.rst
docs/installation.rst
docs/make.bat
docs/readme.rst
docs/tutorial.rst
docs/usage.rst
metaci_cli/__init__.py
metaci_cli/metaci_api.py
metaci_cli.egg-info/PKG-INFO
metaci_cli.egg-info/SOURCES.txt
metaci_cli.egg-info/dependency_links.txt
metaci_cli.egg-info/entry_points.txt
metaci_cli.egg-info/not-zip-safe
metaci_cli.egg-info/requires.txt
metaci_cli.egg-info/top_level.txt
metaci_cli/cli/__init__.py
metaci_cli/cli/config.py
metaci_cli/cli/util.py
metaci_cli/cli/commands/__init__.py
metaci_cli/cli/commands/build.py
metaci_cli/cli/commands/main.py
metaci_cli/cli/commands/org.py
metaci_cli/cli/commands/plan.py
metaci_cli/cli/commands/repo.py
metaci_cli/cli/commands/service.py
metaci_cli/cli/commands/site.py
tests/__init__.py
tests/test_metaci_cli.py