Metadata-Version: 1.1
Name: metaci-cli
Version: 0.1.3
Summary: A command line interface for MetaCI, a CI app run on Heroku for Salesforce development projects
Home-page: https://github.com/jlantz/metaci_cli
Author: Jason Lantz
Author-email: jlantz@salesforce.com
License: BSD license
Keywords: metaci_cli
Platform: UNKNOWN
Classifier: Development Status :: 2 - Pre-Alpha
Classifier: Intended Audience :: Developers
Classifier: License :: OSI Approved :: BSD License
Classifier: Natural Language :: English
Classifier: Programming Language :: Python :: 2
Classifier: Programming Language :: Python :: 2.6
Classifier: Programming Language :: Python :: 2.7
Classifier: Programming Language :: Python :: 3
Classifier: Programming Language :: Python :: 3.3
Classifier: Programming Language :: Python :: 3.4
Classifier: Programming Language :: Python :: 3.5
